mkpypac/MIT-LICENSE-template
mkpypac/__init__.py
mkpypac/main.py
mkpypac/pyproject-template.toml
mkpypac-0.0.1.dist-info/METADATA
mkpypac-0.0.1.dist-info/WHEEL
mkpypac-0.0.1.dist-info/entry_points.txt
mkpypac-0.0.1.dist-info/licenses/LICENSE
mkpypac-0.0.1.dist-info/RECORD
