Metadata-Version: 2.1
Name: mkpypac
Version: 0.0.1
Summary: Python package boilerplate
Project-URL: Homepage, https://github.com/Graphity/mkpypac
Project-URL: Bug Tracker, https://github.com/Graphity/mkpypac/issues
Author: Graphity
License: MIT License
Classifier: License :: OSI Approved :: MIT License
Classifier: Operating System :: OS Independent
Classifier: Programming Language :: Python :: 3
Requires-Python: >=3.7
